<?xml version="1.0" encoding="windows-1251" ?>
<string_table>

<string id="esc_get_tools_1_2_name">
		<text>Tools: Bring tools to Stoepka.</text>
	</string>
	<string id="esc_get_tools_1_2_text">
		<text>Stoepka has asked to find two sets of tools: one for precision work, the other for rough work. The wizard will not only pay for the tool, but can provide more serious upgrades to weapons or body armor.</text>
	</string>
	<string id="esc_get_tools_1_3_name">
		<text>Tools: bring tools to Stoepka</text>
	</string>
	<string id="esc_get_tools_1_3_text">
		<text>Stjepka has asked to find two sets of tools, one for rough work and one for calibration. The wizard will not only pay for the tool, but can also provide a more serious upgrade to the weapon or body armor.</text>
	</string>
	<string id="esc_get_tools_1_name">
		<text>Tools: bring tools to Stoepka</text>
	</string>
	<string id="esc_get_tools_1_text">
		<text>Stoepka has asked to find a set of tools for rough work. The wizard will not only pay for the tool, but can provide a more serious upgrade to the weapon or body armour.</text>
	</string>
	<string id="esc_get_tools_2_3_name">
		<text>Tools: Bring tools to Stoepka</text>
	</string>
	<string id="esc_get_tools_2_3_text">
		<text>Stjepka has asked to find two sets of tools, one for fine work and one for calibration. Not only will the wizard pay for the tool, but he can also provide a more serious upgrade to the weapon or body armour.</text>
	</string>
	<string id="esc_get_tools_2_name">
		<text>Tools: bring tools to Stoepka</text>
	</string>
	<string id="esc_get_tools_2_text">
		<text>Stoepka has asked to find a set of tools for precision work. The wizard will not only pay for the tool, but can also provide a more serious upgrade to his weapon or body armour.</text>
	</string>
	<string id="esc_get_tools_3_name">
		<text>Tools: Bring tools to Stoepka</text>
	</string>
	<string id="esc_get_tools_3_text">
		<text>Stjepka has asked to find a set of tools for calibration. The wizard will not only pay for the tool, but can also provide a more serious upgrade to the weapon or body armour.</text>
	</string>
	<string id="esc_mechanic_toolkit_search_name">
		<text>Tools: Bring tools to Stoepka</text>
	</string>
	<string id="esc_mechanic_toolkit_search_text">
		<text>Stjepka has asked to find three sets of tools: for rough work, for precision work plus a calibration set. Not only will the wizard pay for the tool, but he can provide a more serious upgrade to the weapon or body armor.</text>
	</string>
	
	
	<string id="esc_2get_tools_1_2_name">
		<text>Tools: bring tools to Barkas</text>
	</string>
	<string id="esc_get_tools_1_2_text">
		<text>Stjepka has asked to find two sets of tools, one for precision work and one for rough work. The wizard will not only pay for the tool, but can also provide a more serious upgrade to the weapon or armour.</text>
	</string>
	<string id="esc_2get_tools_1_3_name">
		<text>Tools: bring tools to Barkas</text>
	</string>
	<string id="esc_2get_tools_1_3_text">
		<text>Stjepka asked to find two sets of tools, one for rough work and one for calibration. Not only will the wizard pay for the tool, but he can also provide a more serious upgrade to the weapon or armor.</text>
	</string>
	<string id="esc_2get_tools_1_name">
		<text>Tools: bring tools to Barkas</text>
	</string>
	<string id="esc_2get_tools_1_text">
		<text>Stupka asked to find a set of tools for rough work. The wizard will not only pay for the tool, but can also provide a more serious upgrade to a weapon or body armour.</text>
	</string>
	<string id="esc_2get_tools_2_3_name">
		<text>Tools: bring tools to Barkas</text>
	</string>
	<string id="esc_2get_tools_2_3_text">
		<text>Stjepka asked to find two sets of tools, one for fine work and one for calibration. The wizard will not only pay for the tool, but can also provide a more serious upgrade to the weapon or armour.</text>
	</string>
	<string id="esc_get_tools_2_name">
		<text>Tools: bring tools to Barkas</text>
	</string>
	<string id="esc_2get_tools_2_text">
		<text>Stupka has asked to find a set of tools for precision work. The wizard will not only pay for the tool, but can provide a more serious upgrade to the weapon or body armour.</text>
	</string>
	<string id="esc_2get_tools_3_name">
		<text>Tools: Bring Tools to Barkas</text>
	</string>
	<string id="esc_2get_tools_3_text">
		<text>Stupka asked to find a set of tools for calibration. The wizard will not only pay for the tool, but can provide a more serious upgrade to the weapon or body armour.</text>
	</string>
	<string id="esc_2mechanic_toolkit_search_name">
		<text>Tools: Bring Tools to Barkas</text>
	</string>
	<string id="esc_2mechanic_toolkit_search_text">
		<text>Stjepka has asked to find three sets of tools: for rough work, for precision work plus a calibration set. The wizard will not only pay for the tool, but can provide a more serious upgrade to the weapon or body armour.</text>
	</string>
	
	<string id="esc_risovalshik_items_get_order_name">
		<text>Special order: pick up</text>
	</string>
	<string id="esc_risovalshik_items_get_order_text">
		<text>The order has been delivered, you must pick it up from the Skillet.</text>
	</string>
	<string id="esc_risovalshik_items_wait_order_name">
		<text>Special order: waiting for delivery.</text>
	</string>
	<string id="esc_risovalshik_items_wait_order_text">
		<text>Order has been placed. You must wait until the painter delivers your item.</text>
	</string>
	
	
<!-- Квест:  Вступление в сталкеры -->	
<string id="esc_entry_into_stalkers_name">
<text>Join the Stalkers: Speak to the Shaman</text>
</string>
<string id="esc_entry_into_stalkers_text">
<text>Speak with Shaman to join the Free Stalkers Clan.</text>
</string>
	
	
<!-- Квест: Проход в Зону -->
<string id="esc_the_entrance_to_the_zone_part_1_name">
<text>Entering the Zone: Talk to Borland.</text>
</string>
<string id="esc_the_entrance_to_the_zone_part_1_text">
<text>Re-plan with your partner to break into the Zone through a roadblock.</text>
</string>
<string id="esc_the_entrance_to_the_zone_part_2_name">
<text>Breaking into the Zone: Show IDs</text>
</string>
<string id="esc_the_entrance_to_the_zone_part_2_text">
<text>Show the fake IDs to the checkpoint inspectors.</text>
</string>
<string id="esc_the_entrance_to_the_zone_part_3_name">
<text>Breaking into the Zone: Enter the Zone</text>
</string>
<string id="esc_the_entrance_to_the_zone_part_3_text">
<text>Walk through a checkpoint into the Zone</text>
</string>


<!-- Квест: Плата -->
<string id="esc_quest_fee_part_1_name">
<text>Payment: Collect money</text>
</string>
<string id="esc_quest_fee_part_1_text">
<text>Lieutenant Colonel Kolyazin gave a deadline of only two days. During this time to earn 30,000 rubles.</text>
</string>
<string id="esc_quest_fee_part_2_name">
<text>Payment: Pay for freedom.</text>
</string>
<string id="esc_quest_fee_part_2_text">
<text>The money has been collected. Now they need to give it to Kolyazin and take Borland out of the roadblock</text>
</string>
<string id="esc_quest_fee_part_3a_name">
<text>Payment: Kolyazin's errands</text>
</string>
<string id="esc_quest_fee_part_3a_text">
<text>To free Borland you need to run a couple of errands Koliazin</text>
</string>
<string id="esc_quest_fee_part_3_name">
<text>Payment: talk to Borland.</text>
</string>
<string id="esc_quest_fee_part_3_text">
<text>Tell Borland the good news that he is free.</text>
</string>
<string id="esc_quest_fee_part_4_name">
<text>Payment: Leave the roadblock.</text>
</string>
<string id="esc_quest_fee_part_4_text">
<text>Payment for the freedom is paid in full, you can now quietly leave the unfortunate roadblock.</text>
</string>


<!-- Квест: Забрать свой хабар-->
<string id="esc_quest_free_habar_name">
<text>Get your loot.</text>
</string>
<string id="esc_quest_free_habar_text">
<text>Get your loot from the safe at the exit of the checkpoint.</text>
</string>


<!-- Квест: Безопасное место -->
<string id="eac_reach_base_name">
<text>Safe Haven: Getting to the Rookie Village</text>
</string>
<string id="eac_reach_base_text">
<text>It is relatively safe in the Zone only in the larger camps. It makes sense to get to the closest of them, the Rookie Village.</text>
</string>


<!-- Квест: Первые копейки -->

<string id="esc_the_first_penny_part_1_name">
<text>First pennies: Talk to the Dog.</text>
</string>
<string id="esc_the_first_penny_part_1_text">
<text>Dog is an experienced stalker from the Rookie Village. He can help you earn money.</text>
</string>
<string id="esc_the_first_penny_part_2_name">
<text>First Penny: Walk behind the railway embankment.</text>
</string>
<string id="esc_the_first_penny_part_2_text">
<text>Find a way to get to the other side of the embankment.</text>
</string>
<string id="esc_the_first_penny_part_3_name">
<text>First Penny: Find a missing stalker or his belongings.</text>
</string>
<string id="esc_the_first_penny_part_3_text">
<text>The rookie stalker Dog asked to find was last contacted near the train.</text>
</string>
<string id="esc_the_first_penny_part_4_name">
<text>First pennies: Report your find to Dog</text>
</string>
<string id="esc_the_first_penny_part_4_text">
<text>Give the found items to the Dog or keep them.</text>
</string>


<!-- Квест: Работа для Новичка -->
<string id="esc_quest_work_for_beginner_part_1_name">
<text>Job for Beginner: Talk to Skidan.</text>
</string>
<string id="esc_quest_work_for_beginner_part_1_text">
<text>Talk to the local Trogovian, Skidan may be able to get you some work.</text>
</string>
<string id="esc_quest_work_for_beginner_part_2_name">
<text>Novice Job: Find an Artifact</text>
</string>
<string id="esc_quest_work_for_beginner_part_2_text">
<text>Skidan offers to pass the proficiency test and get an artifact "Crystal" or "Fireball" or "Eye". It's pretty risky business, so you can turn it down.</text>
</string>
<string id="esc_quest_work_for_beginner_part_3_name">
<text>Novice Job: Bringing an artifact.</text>
</string>
<string id="esc_quest_work_for_beginner_part_3_text">
<text>Give the found artifact to Skidan and get a reward.</text>
</string>


<!-- Квест: Поговорить с Псом -->
<string id="esc_quest_talk_wolf_name">
<text>Talk to the Dog.</text>
</string>
<string id="esc_quest_talk_wolf_text">
<text>The Dog has asked to come up and ask him about a case.</text>
</string>


<!-- Квест: Зачистка-->
<string id="eac_quest_trimming_part_1_name">
<text>Sweep: Find a sweep team</text>
</string>
<string id="eac_quest_trimming_part_1_text">
<text>Several stalkers have decided to secure the neighborhood. We need to help them.</text>
</string>
<string id="eac_quest_trimming_part_2_name">
<text>Sweep: Sweep the area</text>
</string>
<string id="eac_quest_trimming_part_2_text">
<text>There are a lot of wild boars and dogs in the area. You must reduce their numbers.</text>
</string>
<string id="eac_quest_trimming_part_3_name">
<text>Sweep: Report back</text>
</string>
<string id="eac_quest_trimming_part_3_text">
<text>Get a reward from the Dog.</text>
</string>


<!-- Квест: Страховка -->
<string id="esc_quest_insurance_part_1_name">
<text>Insurance: talk to the Hound.</text>
</string>
<string id="esc_quest_insurance_part_1_text">
<text>Find out what kind of help is required by the Dog.</text>
</string>
<string id="esc_quest_insurance_part_2_name">
<text>Insurance: Get to the Anomaly.</text>
</string>
<string id="esc_quest_insurance_part_2_text">
<text>Walk with the Dog to the nearest anomalous field.</text>
</string>
<string id="esc_quest_insurance_part_3_name">
<text>Insurance: Watch Dog's back.</text>
</string>
<string id="esc_quest_insurance_part_3_text">
<text>Cover Dog from the mutants while he is researching the anomaly.</text>
</string>
<string id="esc_quest_insurance_part_4_name">
<text>Safeguard: Find an artifact in the anomaly</text>
</string>
<string id="esc_quest_insurance_part_4_text">
<text>Using the detector and bolts, find the artifact in the anomaly field.</text>
</string>
<string id="esc_quest_insurance_part_5_name">
<text>Insure: Show Dog the find</text>
</string>
<string id="esc_quest_insurance_part_5_text">
<text>Show the Medusa artifact found in the anomaly to the Dog</text>
</string>
<string id="esc_quest_insurance_part_6_name">
<text>Insurance: Go back to the camp</text>
</string>
<string id="esc_quest_insurance_part_6_text">
<text>Continue on to the newcomer camp with Pes.</text>
</string>



<!-- Квест: Поговорить с Псом (насчёт работы) -->
<string id="esc_quest_talk_wolf_work_name">
<text>Talk to the Hound about the job</text>
</string>
<string id="esc_quest_talk_wolf_work_text">
<text>The Dog has promised to fit the job in.</text>
</string>


<!-- Квест: Охота -->
<string id="esc_quest_hunting_part_1_name">
<text>Hunting: Find the hunter.</text>
</string>
<string id="esc_quest_hunting_part_1_text">
<text>To the east of the ATP is waiting for a hunter nicknamed Leshy.</text>
</string>
<string id="esc_quest_hunting_part_2_name">
<text>Hunt: Kill a wild boar.</text>
</string>
<string id="esc_quest_hunting_part_2_text">
<text>You and Leshny have to hunt and kill a brown boar.</text>
</string>


<string id="esc_quest_hunting_part_5_name">
<text>Hunting: Save Leshev.</text>
</string>
<string id="esc_quest_hunting_part_5_text">
<text>Leshny was wounded by a boar, you should share a medical kit with him.</text>
</string>



<string id="esc_quest_hunting_part_3_name">
<text>Hunt: Escort the wounded man to the ATP</text>
</string>
<string id="esc_quest_hunting_part_3_text">
<text>Leshny is wounded and cannot carry a weapon himself. You must take him to the nearest medic.</text>
</string>
<string id="esc_quest_hunting_part_4_name">
<text>Hunting: Speak to the leader of the Free Stalkers.</text>
</string>
<string id="esc_quest_hunting_part_4_text">
<text>Tell Shaman what happened.</text>
</string>

<!-- Квест:  Работа -->
<string id="esc_quest_shaman_worke_name">
<text>Talk to the Shaman about a job.</text>
</string>
<string id="esc_quest_shaman_worke_text">
<text>Shaman offers to make extra money, discuss details.</text>
</string>

<!-- Квест: Слежка -->
<string id="esc_quest_shadowing_part_1_name">
<text>Stalking: Follow Sawyer.</text>
</string>
<string id="esc_quest_shadowing_part_1_text">
<text>Clandestinely follow Sawyer, find out where he hid the stolen loot from the clan's cache.</text>
</string>
<string id="esc_quest_shadowing_part_2_name">
<text>Surveillance: Catch Sawyer off guard.</text>
</string>
<string id="esc_quest_shadowing_part_2_text">
<text>Expose Sawyer, talk to him about the stolen cache.</text>
</string>
<string id="esc_quest_shadowing_part_3_name">
<text>Stalking: Talking to the Shaman.</text>
</string>
<string id="esc_quest_shadowing_part_3_text">
<text>Trick Shaman into giving Sawyer the left coordinates of the cache.</text>
</string>


<!-- Квест: Борьба за территорию -->
<string id="esc_quest_fighting_for_territory_part_1_name">
<text>Fighting for territory: Talk to Cousteau.</text>
</string>
<string id="esc_quest_fighting_for_territory_part_1_text">
<text>Talk to Cousteau's trader, about the job.</text>
</string>
<string id="esc_quest_fighting_for_territory_part_2_name">
<text>Fighting for territory: Destroy bandits.</text>
</string>
<string id="esc_quest_fighting_for_territory_part_2_text">
<text>Eliminate the bandits stationed near the ATP. This helps to stop the looting of Stalkers who return with loot to the base.</text>
</string>
<string id="esc_quest_fighting_for_territory_part_3_name">
<text>Fighting for your territory: Get the reward</text>
</string>
<string id="esc_quest_fighting_for_territory_part_3_text">
<text>Collect your reward for eliminating bandits from the merchant.</text>
</string>


<!-- Квест: Плевое дело -->
<string id="esc_quest_trifling_matter_part_1_name">
<text>Naughty Business: Talking to Skidan.</text>
</string>
<string id="esc_quest_trifling_matter_part_1_text">
<text>A local merchant wants to ask you something. Best not to refuse.</text>
</string>
<string id="esc_quest_trifling_matter_part_2_name">
<text>Dirty Deed: Take a parcel to the ATP.</text>
</string>
<string id="esc_quest_trifling_matter_part_2_text">
<text>This mission is the easiest of all tasks: deliver the parcel to the stalker.</text>
</string>
<string id="esc_quest_trifling_matter_part_3_name">
<text>Nifty Business: Decide the fate of the parcel</text>
</string>
<string id="esc_quest_trifling_matter_part_3_text">
<text>Split the content of the parcel or deliver it to the address.</text>
</string>
<string id="esc_quest_trifling_matter_part_4_name">
<text>Naughty Business: Report to Skidan</text>
</string>
<string id="esc_quest_trifling_matter_part_4_text">
<text>Getting paid for the job from Skidan.</text>
</string>
<string id="esc_quest_trifling_matter_part_5_name">
<text>Dumb thing to do: Make up an excuse</text>
</string>
<string id="esc_quest_trifling_matter_part_5_text">
<text>Tell Skidan about the imaginary thugs who stole the package.</text>
</string>


<!-- Квест: Серьезное дело -->
<string id="esc_quest_serious_business_part_1_name">
<text>Serious business: Talk to Skidan.</text>
</string>
<string id="esc_quest_serious_business_part_1_text">
<text>Skidan wants to offer some serious work, talk to him about the details.</text>
</string>
<string id="esc_quest_serious_business_part_2_name">
<text>Serious business: Ask the stalkers about the debtor.</text>
</string>
<string id="esc_quest_serious_business_part_2_text">
<text>Find out where the missing debtor stalker was last seen.</text>
</string>
<string id="esc_quest_serious_business_part_3_name">
<text>Serious Business: Investigate possible Debtor's hideouts.</text>
</string>
<string id="esc_quest_serious_business_part_3_text">
<text>Debtor's stalker may be hiding out at the grain elevator, in the house across from the farm.</text>
</string>
<string id="esc_quest_serious_business_part_4_name">
<text>Serious Thing: Search a dead body.</text>
</string>
<string id="esc_quest_serious_business_part_4_text">
<text>Search the corpse of a bandit.</text>
</string>
<string id="esc_quest_serious_business_part_5_name">
<text>Serious business: Search the last hideout at the checkpoint</text>
</string>
<string id="esc_quest_serious_business_part_5_text">
<text>The message on the PDA of the murdered bandit, says Shmyga and his company went to the checkpoint in the direction of the dump.</text>
</string>
<string id="esc_quest_serious_business_part_6_name">
<text>Serious business: Run or fight.</text>
</string>
<string id="esc_quest_serious_business_part_6_text">
<text>Take out the debtor's accomplices or go back to Skidan.</text>
</string>


<!-- Квест: Серьезное дело -->
<string id="esc_quest_dangerous_business_part_1_name">
<text>Serious Business: Talk to Skidan.</text>
</string>
<string id="esc_quest_dangerous_business_part_1_text">
<text>Talk to Skidan about the case.</text>
</string>
<string id="esc_quest_dangerous_business_part_2_name">
<text>Serious Business: Meet Mercenaries</text>
</string>
<string id="esc_quest_dangerous_business_part_2_text">
<text>You must bring the mercenaries an advance payment.</text>
</string>
<string id="esc_quest_dangerous_business_part_3_name">
<text>Serious Business: Kill Shmyga</text>
</string>
<string id="esc_quest_dangerous_business_part_3_text">
<text>Kill Shmyga and take from him the keys to the safe where the case with the money is hidden.</text>
</string>
<string id="esc_quest_dangerous_business_part_4_name">
<text>Serious Business: Taking the money box.</text>
</string>
<string id="esc_quest_dangerous_business_part_4_text">
<text>Open the safe and retrieve the cash case.</text>
</string>
<string id="esc_quest_dangerous_business_part_5_name">
<text>Serious Deed: Get reward.</text>
</string>
<string id="esc_quest_dangerous_business_part_5_text">
<text>Return to Skidan to drop the case and collect your reward.</text>
</string>
<string id="esc_quest_dangerous_business_part_6_name">
<text>Serious Business: Find a way to get the case back.</text>
</string>
<string id="esc_quest_dangerous_business_part_6_text">
<text>Now that Shmyga is in the Bandit base, there is no easy way to retrieve his loot.</text>
</string>


<!-- Квест: Гоп-стоп -->

<string id="esc_quest_gopstop_part_1_name">
<text>Gop-Stop: Talk to The Mouthpiece.</text>
</string>
<string id="esc_quest_gopstop_part_1_text">
<text>The leader of the bandits The Mouthpiece wants to offer a job, ignore his offer or discuss the details with him.</text>
</string>
<string id="esc_quest_gopstop_part_2_name">
<text>Gop-Stop: Rob a stalker</text>
</string>
<string id="esc_quest_gopstop_part_2_text">
<text>Ambush a stalker returning from a trip.</text>
</string>
<string id="esc_quest_gopstop_part_3_name">
<text>Gop Stop: Kill or Release Stalker</text>
</string>
<string id="esc_quest_gopstop_part_3_text">
<text>Decide what to do with the stalker.</text>
</string>
<string id="esc_quest_gopstop_part_4_name">
<text>Gop-Stop: Report to the Speech Therapist.</text>
</string>
<string id="esc_quest_gopstop_part_4_text">
<text>Get a reward from the boss.</text>
</string>

<!-- Квест: Механник для бандитов -->
<string id="esc_quest_mechanic_search_part_1_name">
<text>Mechanik for Bandits: Find a Mechanik.</text>
</string>
<string id="esc_quest_mechanic_search_part_1_text">
<text>The Mohawk asks to find a mechanic for his brigade.</text>
</string>
<string id="esc_quest_mechanic_search_part_2_name">
<text>Mechanik for Bandits: Talk to The Mohawk.</text>
</string>
<string id="esc_quest_mechanic_search_part_2_text">
<text>Talk to the speech therapist to find a machinist</text>
</string>
<string id="esc_quest_mechanic_search_part_3_name">
<text>Gunslinger for Gangsters: Talk to the Mentor.</text>
</string>
<string id="esc_quest_mechanic_search_part_3_text">
<text>Report back to the Speech Therapist on the task</text>
</string>

<!-- Квест: Преступный бизнес -->
<string id="esc_quest_criminal_business_part_1_name">
<text>Crime Business: Talk to the Speech Therapist.</text>
</string>
<string id="esc_quest_criminal_business_part_1_text">
<text>Apparently the Speech Therapist is having a showdown with one of his own</text>
</string>
<string id="esc_quest_criminal_business_part_2_name">
<text>Crime Business: Talk to Shmyga.</text>
</string>
<string id="esc_quest_criminal_business_part_2_text">
<text>Convince Shmyga to pay into the joint.</text>
</string>
<string id="esc_quest_criminal_business_part_2a_name">
<text>Crime Business: Punish Shmyga</text>
</string>
<string id="esc_quest_criminal_business_part_2a_text">
<text>Undercut the enemy</text>
</string>
<string id="esc_quest_criminal_business_part_3_name">
<text>Crime Business: Retrieve his belongings</text>
</string>
<string id="esc_quest_criminal_business_part_3_text">
<text>Get your belongings out of the safe</text>
</string>
<string id="esc_quest_criminal_business_part_4_name">
<text>Crime Business: Talk to the speech therapist</text>
</string>
<string id="esc_quest_criminal_business_part_4_text">
<text>Talk to the speech therapist about the situation</text>
</string>


<!-- Квест:  Поговорить с Псом (насчёт работы Проводником) -->
<string id="esc_quest_wolf_work_conductor_name">
<text>Talk to the Dog about the job</text>
</string>
<string id="esc_quest_wolf_work_conductor_text">
<text>Dog offers to work, discuss details.</text>
</string>

<!-- Квест: Првоводник -->
<string id="esc_quest_conductor_part_1_name">
<text>Guide: talk to Student</text>
</string>
<string id="esc_quest_conductor_part_1_text">
<text>Talk to Student about going to the ATP.</text>
</string>
<string id="esc_quest_conductor_part_2_name">
<text>Guide: Guide the Student to the bus station.</text>
</string>
<string id="esc_quest_conductor_part_2_text">
<text>Walk Student to the stalker base at the railroad station.</text>
</string>
<string id="esc_quest_conductor_part_3_name">
<text>Guide: Talk to Student</text>
</string>
<string id="esc_quest_conductor_part_3_text">
<text>Talk to the Student.</text>
</string>
<string id="esc_quest_conductor_part_4_name">
<text>Guide: go back to the Hound to get your reward.</text>
</string>
<string id="esc_quest_conductor_part_4_text">
<text>Collect the rest of the Student's fee from Dog.</text>
</string>


<!-- Квест: Ночная охота -->
<string id="esc_quest_night_hunting_part_1_name">
<text>Night Hunt: Wait for night</text>
</string>
<string id="esc_quest_night_hunting_part_1_text">
<text>Wait until nightfall to hunt down the mutant who is terrorizing the stalker camp.</text>
</string>
<string id="esc_quest_night_hunting_part_2_name">
<text>Night Hunt: Kill a mutant.</text>
</string>
<string id="esc_quest_night_hunting_part_2_text">
<text>Kill the pseudo-mutant that is terrorizing the stalker camp.</text>
</string>
<string id="esc_quest_night_hunting_part_3_name">
<text>Night Hunt: Get Reward</text>
</string>
<string id="esc_quest_night_hunting_part_3_text">
<text>Get a reward from Pathogenic for killing a dangerous mutant.</text>
</string>

<!-- Квест: Поговорить с Борландом -->
<string id="esc_quest_line_meet_borland_name">
<text>Talk to Borland</text>
</string>
<string id="esc_quest_line_meet_borland_text">
<text>Talk to Borland.</text>
</string>

<!-- Квест: Поговорить с Патогенычем -->
<string id="esc_quest_line_meet_patogen_name">
<text>Talk to Pathogenic.</text>
</string>
<string id="esc_quest_line_meet_patogen_text">
<text>ATP bar bartender offers a well-paying job.</text>
</string>


<!-- Квест: Пропавший связной -->
<string id="esc_quest_line_missing_connected_part_1_name">
<text>Missing contact: Cross the railway embankment</text>
</string>
<string id="esc_quest_line_missing_connected_part_1_text">
<text>The missing contact has gone missing somewhere behind the railway embankment, near the bandit base.</text>
</string>
<string id="esc_quest_line_missing_connected_part_2_name">
<text>Missing contact: Follow the bandit</text>
</string>
<string id="esc_quest_line_missing_connected_part_2_text">
<text>Follow the bandit Sleeper, try not to scare him off.</text>
</string>
<string id="esc_quest_line_missing_connected_part_3_name">
<text>Missing Messenger: Search the Bandit</text>
</string>
<string id="esc_quest_line_missing_connected_part_3_text">
<text>Search the corpse of the bandit Sleeper.</text>
</string>
<string id="esc_quest_line_missing_connected_part_4_name">
<text>Missing Liaison : foil the Bandit's plan.</text>
</string>
<string id="esc_quest_line_missing_connected_part_4_text">
<text>The bandits have decided to finish off the captured freedom fighter to stop the mayhem.</text>
</string>
<string id="esc_quest_line_missing_connected_part_5_name">
<text>Missing Contact: Tell Pathogenic what happened.</text>
</string>
<string id="esc_quest_line_missing_connected_part_5_text">
<text>The messenger is dead, tell Patogenych that bandits are involved, tell about the captured freedom fighter.</text>
</string>


<!-- Квест: Спасение свободовца -->
<string id="esc_quest_line_salvation_freedom_name">
<text>Saving the freedom fighter: save the freedom fighter</text>
</string>
<string id="esc_quest_line_salvation_freedom_text">
<text>Bandits near the ruins are holding a freedom fighter captive, rescue him from captivity.</text>
</string>
<string id="esc_quest_line_salvation_freedom_name_2">
<text>Rescuing the freedom fighter: Tell Pathogenic what happened.</text>
</string>
<string id="esc_quest_line_salvation_freedom_text_2">
<text>Tell about the suicide of a freedom fighter.</text>
</string>


<!-- Квест: Тайна свободовца -->
<string id="esc_quest_line_secret_freedom_part_1_name">
<text>The mystery of the freedom fighter: Search the corpse.</text>
</string>
<string id="esc_quest_line_secret_freedom_part_1_text">
<text>Search the corpse of the Liberator's suicide.</text>
</string>
<string id="esc_quest_line_secret_freedom_part_2_name">
<text>Libertarian's Secret: Unlock the PDA</text>
</string>
<string id="esc_quest_line_secret_freedom_part_2_text">
<text>Go to the mechanic Stoepka, perhaps he can unlock the PDA.</text>
</string>
<string id="esc_quest_line_secret_freedom_part_3_name">
<text>Liberator's Secret: Wait for the PDA to be unlocked.</text>
</string>
<string id="esc_quest_line_secret_freedom_part_3_text">
<text>It will take some time for Stoepka to unlock the PDA. While he unlocks it, help the Shaman with one thing.</text>
</string>
<string id="esc_quest_line_secret_freedom_part_4_name">
<text>The mystery of the freedom fighter: Get the PDA.</text>
</string>
<string id="esc_quest_line_secret_freedom_part_4_text">
<text>Enough time has passed, it's been a long time since Steppe unlocked the PDA.</text>
</string>
<string id="esc_quest_line_secret_freedom_part_5_name">
<text>The Liberator's Secret: Find out where Stjepka's gone.</text>
</string>
<string id="esc_quest_line_secret_freedom_part_5_text">
<text>Stjepka is missing somewhere, ask Patogenic where he could have gone.</text>
</string>
<string id="esc_quest_line_secret_freedom_part_6_name">
<text>The Liberator's Secret: To get to the elevator</text>
</string>
<string id="esc_quest_line_secret_freedom_part_6_text">
<text>Patogenych says that he heard from the walkers that they saw Stepka going to the elevator.</text>
</string>
<string id="esc_quest_line_secret_freedom_part_7_name">
<text>Svoboda's secret: Search the corpse</text>
</string>
<string id="esc_quest_line_secret_freedom_part_7_text">
<text>Stjepka is dead. Search his corpse.</text>
</string>


<!-- Квест: Странное дело-->
<string id="esc_quest_line_help_nebo_part_1_name">
<text>Strange Business: Talk to the Shaman</text>
</string>
<string id="esc_quest_line_help_nebo_part_1_text">
<text>Find out what kind of help the Shaman needs.</text>
</string>
<string id="esc_quest_line_help_nebo_part_2_name">
<text>Strange Business: Talk to Skidan.</text>
</string>
<string id="esc_quest_line_help_nebo_part_2_text">
<text>Shaman asks to go to Skidan for something.</text>
</string>
<string id="esc_quest_line_help_nebo_part_3_name">
<text>Odd Business: Return to the Shaman.</text>
</string>
<string id="esc_quest_line_help_nebo_part_3_text">
<text>Take an unknown piece of equipment to the Shaman.</text>
</string>


<!-- Квест: Поговорить с Борландом в Деревне новичков -->
<string id="esc_quest_line_important_meet_borland_name">
<text>Talk to Borland.</text>
</string>
<string id="esc_quest_line_important_meet_borland_text">
<text>Tell Borland about your adventures: about the mysterious monolithic man in freedom form and about the mysterious artifact.</text>
</string>


<!-- Квест:  В гостях у бандитов-->
<string id="esc_quest_line_away_from_the_bandits_part_1_name">
<text>Visiting Bandits: Speak to the Speech Therapist.</text>
</string>
<string id="esc_quest_line_away_from_the_bandits_part_1_text">
<text>Ask the leader of the bandits about the freedom monolith.</text>
</string>
<string id="esc_quest_line_away_from_the_bandits_part_2_name">
<text>Back to the bandits: Go back to Borland.</text>
</string>
<string id="esc_quest_line_away_from_the_bandits_part_2_text">
<text>Bandits denied help, go back with nothing to Borland</text>
</string>
<string id="esc_quest_line_away_from_the_bandits_part_3_name">
<text>Outlaw Guest: Waiting for help.</text>
</string>
<string id="esc_quest_line_away_from_the_bandits_part_3_text">
<text>Waiting for help from Borland.</text>
</string>
<string id="esc_quest_line_away_from_the_bandits_part_4_name">
<text>Visiting Bandits: Talk to Borland.</text>
</string>
<string id="esc_quest_line_away_from_the_bandits_part_4_text">
<text>Talk to Borland.</text>
</string>


<!-- Квест:  Подземелье-->
<string id="esc_quest_line_dungeon_part_1_name">
<text>Dungeons: Find Watchmaker.</text>
</string>
<string id="esc_quest_line_dungeon_part_1_text">
<text>Stalker Watchmaker lives on the outskirts of the newbie village.</text>
</string>
<string id="esc_quest_line_dungeon_part_2_name">
<text>Dungeon: Talk to the Dog.</text>
</string>
<string id="esc_quest_line_dungeon_part_2_text">
<text>The Watchman isn't at home, so maybe the Dog knows where to find him.</text>
</string>
<string id="esc_quest_line_dungeon_part_3_name">
<text>Dungeon: Meet the Watchdog.</text>
</string>
<string id="esc_quest_line_dungeon_part_3_text">
<text>The Dog tells us the Watchdog is currently returning from the Swamp, so you should meet him and ask about the dungeons.</text>
</string>
<string id="esc_quest_line_dungeon_part_4_name">
<text>Dungeon: Help the Watchmaker</text>
</string>
<string id="esc_quest_line_dungeon_part_4_text">
<text>Help the Watchmaker with the mutants.</text>
</string>
<string id="esc_quest_line_dungeon_part_5_name">
<text>Dungeon: Speak to the Watchmaker.</text>
</string>
<string id="esc_quest_line_dungeon_part_5_text">
<text>Ask the Watchmaker about a dungeon.</text>
</string>
<string id="esc_quest_line_dungeon_part_6_name">
<text>Dungeon: Talk to Borland.</text>
</string>
<string id="esc_quest_line_dungeon_part_6_text">
<text>Tell Borland about the dungeon.</text>
</string>
<string id="esc_quest_line_dungeon_part_7_name">
<text>Dungeon: Go to the dungeon.</text>
</string>
<string id="esc_quest_line_dungeon_part_7_text">
<text>Go underground with Borland.</text>
</string>


<!-- Квест:  Исследование подземелья-->
<string id="esc_quest_line_research_underground_part_1_name">
<text>Dungeon Exploration: Follow Borland.</text>
</string>
<string id="esc_quest_line_research_underground_part_1_text">
<text>Follow Borland.</text>
</string>
<string id="esc_quest_line_research_underground_part_2_name">
<text>Dungeon Exploration: Speak to Skidan.</text>
</string>
<string id="esc_quest_line_research_underground_part_2_text">
<text>This is the encounter, ask Skidan about dungeons.</text>
</string>
<string id="esc_quest_line_research_underground_part_3_name">
<text>Dungeon Exploration: Speak to Borland</text>
</string>
<string id="esc_quest_line_research_underground_part_3_text">
<text>Discuss Skidan's suggestion.</text>
</string>
<string id="esc_quest_line_research_underground_part_4_name">
<text>Dungeon Exploration: Get out of the dungeon</text>
</string>
<string id="esc_quest_line_research_underground_part_4_text">
<text>Get out of a dungeon through a tube.</text>
</string>
<string id="esc_quest_line_research_underground_part_5_name">
<text>Dungeon Exploration: Speak to the Clockmaker.</text>
</string>
<string id="esc_quest_line_research_underground_part_5_text">
<text>Find out about the lab from the Watchmaker and get the access code.</text>
</string>
<string id="esc_quest_line_research_underground_part_6_name">
<text>Dungeon Exploration: Speak to Skidan.</text>
</string>
<string id="esc_quest_line_research_underground_part_6_text">
<text>Accept Skidan's demands and ask him for the laboratory access code.</text>
</string>
<string id="esc_quest_line_research_underground_part_7_name">
<text>Dungeon Exploration: Speak to Borland</text>
</string>
<string id="esc_quest_line_research_underground_part_7_text">
<text>Talk to Borland about getting down to the lab.</text>
</string>
<string id="esc_quest_line_research_underground_part_8_name">
<text>Dungeon Exploration: Follow Borland</text>
</string>
<string id="esc_quest_line_research_underground_part_8_text">
<text>Follow Borland into the lab.</text>
</string>
<string id="esc_quest_line_research_underground_part_9_name">
<text>Dungeon Exploration: Go down to the lab.</text>
</string>
<string id="esc_quest_line_research_underground_part_9_text">
<text>Open door to lab, access code: 7200.</text>
</string>
<string id="esc_quest_line_research_underground_part_10_name">
<text>Dungeon Exploration: Descend into the lab</text>
</string>
<string id="esc_quest_line_research_underground_part_10_text">
<text>Descend into the lab.</text>
</string>

<!-- Квест:  Теперь ты в армии 1-->
<string id="esc_quest_army_contract_1_part_1_name">
<text>You are now in the army: Chimera's Den</text>
</string>
<string id="esc_quest_army_contract_1_part_1_text">
<text>Sneak into the Chimera's Den.</text>
</string>
<string id="esc_quest_army_contract_1_part_2_name">
<text>You're in the army now: Kill a chimera or...</text>
</string>
<string id="esc_quest_army_contract_1_part_2_text">
<text>Kill a chimera or...</text>
</string>
<string id="esc_quest_army_contract_1_part_3_name">
<text>You're in the army now: Get the PDA</text>
</string>
<string id="esc_quest_army_contract_1_part_3_text">
<text>Get the Warrant Officer's PDA with valuable military information</text>
</string>
<string id="esc_quest_army_contract_1_part_4_name">
<text>Now you're in the army: Report to Kolyazin</text>
</string>
<string id="esc_quest_army_contract_1_part_4_text">
<text>Return the PDA.</text>
</string>


<!-- Квест:  Теперь ты в армии 2-->
<string id="esc_quest_army_contract_2_part_1_name">
<text>You're now in the army: Find the Deserter</text>
</string>
<string id="esc_quest_army_contract_2_part_1_text">
<text>Find the Deserter. Ask around at Cordon.</text>
</string>
<string id="esc_quest_army_contract_2_part_2_name">
<text>You're in the army now: Report to Kolyazin.</text>
</string>
<string id="esc_quest_army_contract_2_part_2_text">
<text>Tell the truth or report the Deserter's death.</text>
</string>

	<!-- esc_mechanic_furgon -->
	<string id="esc_mechanic_furgon_task_1_name">
		<text>Find %s for Steppe.</text>
	</string>
	<string id="esc_mechanic_furgon_task_1_text">
		<text>You need to bring tools to Stoepke, so he can upgrade his equipment.</text>
	</string>
	<string id="esc_mechanic_furgon_task_1_about">
		<text>You know, bro, I'm actually not a bad technician. And weapons and armor know how to repair, even upgrade some or other do! Or rather, I would do them, if I had proper tools. But where to get them here? Maybe you can help me get a simple kit, huh?</text>
	</string>
	<string id="esc_mechanic_furgon_task_1_fetch_about">
		<text>I need a tool kit for rough work. It's got to have tools and oils for working with guns. If you can get me one, I'd appreciate it, even pay you. I guess.</text>
	</string>
	<string id="esc_mechanic_furgon_task_1_fetch_finish">
		<text>All right, man! Oh, I'm sorry, I can't pay you. But I can give you a good discount!</text>
	</string>
	<string id="esc_mechanic_furgon_task_2_name">
		<text>Find %s for Stoepke.</text>
	</string>
	<string id="esc_mechanic_furgon_task_2_text">
		<text>We need to get Stoepka some tools for his delicate work. He needs a more complete set in order to do more complex gear upgrades.</text>
	</string>
	<string id="esc_mechanic_furgon_task_2_about">
		<text>Hey, dude, if you agree to get me a more complete set, you'll get an even bigger discount. Can you help me out, buddy?</text>
	</string>
	<string id="esc_mechanic_furgon_task_2_fetch_about">
		<text>I need tools to do some fine work. Should have everything I need in there. You'd be like a brother to me if you got it!</text>
	</string>
	<string id="esc_mechanic_furgon_task_2_fetch_finish">
		<text>Wow, man, thanks, bro! Now I'm gonna be rich for sure. Damn it, I'm gonna be successful... Unless, of course, I miss this chance. But for now, I can't offer you anything better than a discount. Sorry, buddy.</text>
	</string>
	<string id="esc_mechanic_furgon_task_3_name">
		<text>Find %s for Stoepke.</text>
	</string>
	<string id="esc_mechanic_furgon_task_3_text">
		<text>We need to get %s for Stoepka. He needs a unique kit to do even more sophisticated gear upgrades.</text>
	</string>
	<string id="esc_mechanic_furgon_task_3_about">
		<text>Hey, man, if you find something good, I'll give you a discount.</text>
	</string>
	<string id="esc_mechanic_furgon_task_3_fetch_about">
		<text>I need calibration tools. They should have everything I need. You'll be like a brother to me if you get them!</text>
	</string>
	<string id="esc_mechanic_furgon_task_3_fetch_finish">
		<text>No hoo...! Damn, thanks, bro! Now I'm gonna be rich for sure. Goddamn it, I'm gonna be successful... Unless, of course, I miss this chance. But I can't offer you anything better than a discount. Sorry, mate.</text>
	</string>

	<!-- esc_mechanic_barkas -->
	<string id="esc_mechanic_barkas_task_1_name">
		<text>Find for Barkas %s.</text>
	</string>
	<string id="esc_mechanic_barkas_task_1_text">
		<text>We need to get tools for Barkas so he can upgrade his gear.</text>
	</string>
	<string id="esc_mechanic_barkas_task_1_about">
		<text>You know, bro, I'm actually a pretty good technician. I can mend weapons and armour, and even make upgrades of sorts. Or rather, I would do them if I had proper tools. But where to get them here? Maybe you can help me get a simple kit, huh?</text>
	</string>
	<string id="esc_mechanic_barkas_task_1_fetch_about">
		<text>I need a tool kit for rough work. It's got to have tools and oils for working with guns. If you can get me one, I'd appreciate it, even pay you. I guess.</text>
	</string>
	<string id="esc_mechanic_barkas_task_1_fetch_finish">
		<text>All right, man! Oh, I'm sorry, I can't pay you. But I can give you a good discount!</text>
	</string>
	<string id="esc_mechanic_barkas_task_2_name">
		<text>Find for Barkas %s.</text>
	</string>
	<string id="esc_mechanic_barkas_task_2_text">
		<text>You need to get Barkas some tools for fine work. He needs a more complete set in order to do more complex gear upgrades.</text>
	</string>
	<string id="esc_mechanic_barkas_task_2_about">
		<text>Hey man, if you agree to get me a more complete kit, you'll get an even bigger discount. Can you help me out, buddy?</text>
	</string>
	<string id="esc_mechanic_barkas_task_2_fetch_about">
		<text>I need tools to do some fine work. Should have everything I need in there. You'd be like a brother to me if you got it!</text>
	</string>
	<string id="esc_mechanic_barkas_task_2_fetch_finish">
		<text>Wow, man, thanks, bro! Now I'm gonna be rich for sure. Damn it, I'm gonna be successful... Unless, of course, I miss this chance. But for now, I can't offer you anything better than a discount. Sorry, mate.</text>
	</string>
	<string id="esc_mechanic_barkas_task_3_name">
		<text>Find for Barkas %s.</text>
	</string>
	<string id="esc_mechanic_barkas_task_3_text">
		<text>You need to get Barkas the %s. He needs a unique kit to do even more sophisticated gear upgrades.</text>
	</string>
	<string id="esc_mechanic_barkas_task_3_about">
		<text>Hey, kid, if you find something good, I'll give you a discount.</text>
	</string>
	<string id="esc_mechanic_barkas_task_3_fetch_about">
		<text>I need calibration tools. They should have everything I need. You'll be like a brother to me if you get them!</text>
	</string>
	<string id="esc_mechanic_barkas_task_3_fetch_finish">
		<text>No hoo...! Damn, thanks, bro! Now I'm gonna be rich for sure. Goddamn it, I'm gonna be successful... Unless, of course, I miss this chance. But I can't offer you anything better than a discount. Sorry, buddy.</text>
	</string>

</string_table>
